README.md
setup.py
tart_web_api/__init__.py
tart_web_api/config.py
tart_web_api/database.py
tart_web_api/main.py
tart_web_api/service.py
tart_web_api/tart_dummy_spi.py
tart_web_api/views.py
tart_web_api/views_acquisition.py
tart_web_api/views_auth.py
tart_web_api/views_cache.py
tart_web_api/views_cal.py
tart_web_api/views_channel.py
tart_web_api/views_log.py
tart_web_api/views_obs.py
tart_web_api.egg-info/PKG-INFO
tart_web_api.egg-info/SOURCES.txt
tart_web_api.egg-info/dependency_links.txt
tart_web_api.egg-info/requires.txt
tart_web_api.egg-info/top_level.txt