Metadata-Version: 2.1
Name: tart-web-api
Version: 0.1.9
Summary: Transient Array Radio Telescope High-level HTTP Interface
Home-page: http://github.com/tmolteno/TART
Author: Tim Molteno, Max Scheel, Pat Suggate
Author-email: tim@elec.ac.nz
License: GPLv3
Platform: UNKNOWN
